mypytoolkit/__init__.py
mypytoolkit/backoff.py
mypytoolkit/dates.py
mypytoolkit/files.py
mypytoolkit/finance.py
mypytoolkit/math.py
mypytoolkit/pyfuncs.py
mypytoolkit/threadtools.py
mypytoolkit/web.py
mypytoolkit-1.6.1.dist-info/METADATA
mypytoolkit-1.6.1.dist-info/WHEEL
mypytoolkit-1.6.1.dist-info/top_level.txt
mypytoolkit-1.6.1.dist-info/RECORD
