Metadata-Version: 2.1
Name: mypytoolkit
Version: 1.6.1
Summary: Basic tools I feel are missing in the standard Python distribution.
Author: Prerit Das
Author-email: <preritdas@gmail.com>
Keywords: python,tools
Classifier: Programming Language :: Python :: 3
Classifier: Operating System :: Unix
Classifier: Operating System :: MacOS :: MacOS X
Classifier: Operating System :: Microsoft :: Windows
Requires-Dist: DateTime
Requires-Dist: matplotlib
Requires-Dist: numpy
Requires-Dist: pandas
